{
  "$schema": "https://schemas.wp.org/trunk/block.json",
  "apiVersion": 3,
  "name": "design-system/scrolling-progress",
  "version": "0.1.0",
  "title": "Design System Scrolling Progress",
  "category": "widgets",
  "icon": "media-interactive",
  "description": "An interactive block with the Interactivity API",
  "example": {},
  "supports": {
    "anchor": true,
    "align": true,
    "layout": {
      "allowOrientation": true,
      "allowInheriting": true
    },
    "ariaLabel": true,
    "background": {
      "backgroundImage": true,
      "backgroundSize": true
    },
    "interactivity": true
  },
  "textdomain": "design-system-scrolling-progress",
  "editorScript": "file:./index.js",
  "editorStyle": "file:./index.css",
  "style": "file:./style-index.css",
  "render": "file:./render.php",
  "viewScriptModule": "file:./view.js"
}